LICENSE.md
MANIFEST.in
README.md
pyproject.toml
src/quansino/__init__.py
src/quansino/constraints.py
src/quansino/protocols.py
src/quansino/py.typed
src/quansino/registry.py
src/quansino/type_hints.py
src/quansino.egg-info/PKG-INFO
src/quansino.egg-info/SOURCES.txt
src/quansino.egg-info/dependency_links.txt
src/quansino.egg-info/requires.txt
src/quansino.egg-info/top_level.txt
src/quansino/integrators/__init__.py
src/quansino/integrators/core.py
src/quansino/integrators/displacement.py
src/quansino/io/__init__.py
src/quansino/io/core.py
src/quansino/io/file.py
src/quansino/io/logger.py
src/quansino/io/restart.py
src/quansino/io/trajectory.py
src/quansino/mc/__init__.py
src/quansino/mc/canonical.py
src/quansino/mc/contexts.py
src/quansino/mc/core.py
src/quansino/mc/criteria.py
src/quansino/mc/driver.py
src/quansino/mc/fbmc.py
src/quansino/mc/gcmc.py
src/quansino/mc/isobaric.py
src/quansino/mc/isotension.py
src/quansino/moves/__init__.py
src/quansino/moves/cell.py
src/quansino/moves/composite.py
src/quansino/moves/core.py
src/quansino/moves/displacement.py
src/quansino/moves/exchange.py
src/quansino/operations/__init__.py
src/quansino/operations/cell.py
src/quansino/operations/composite.py
src/quansino/operations/core.py
src/quansino/operations/displacement.py
src/quansino/utils/__init__.py
src/quansino/utils/atoms.py
src/quansino/utils/dynamics.py
src/quansino/utils/moves.py
src/quansino/utils/strings.py
tests/test_registry.py