Metadata-Version: 2.4
Name: quansino
Version: 0.1.3
Summary: `quansino` is a modular package based on the Atomic Simulation Environment (ASE) for quickly building custom Monte Carlo algorithms
Author-email: Tom Demeyere <tom.dmre@gmail.com>
License: BSD-3
Project-URL: repository, https://github.com/Atomic-Samplers/quansino
Project-URL: documentation, https://atomic-samplers.github.io/quansino/
Project-URL: changelog, https://github.com/Atomic-Samplers/quansino/blob/main/CHANGELOG.md
Keywords: Monte Carlo,Computational Chemistry,Quantum Chemistry
Classifier: Development Status :: 3 - Alpha
Classifier: Intended Audience :: Science/Research
Classifier: Programming Language :: Python :: 3
Classifier: Programming Language :: Python :: 3.11
Classifier: Programming Language :: Python :: 3.12
Classifier: Programming Language :: Python :: 3.13
Classifier: Intended Audience :: Science/Research
Classifier: Topic :: Scientific/Engineering
Classifier: Operating System :: Microsoft :: Windows
Classifier: Operating System :: Unix
Classifier: Operating System :: MacOS
Requires-Python: >=3.11
License-File: LICENSE.md
Requires-Dist: numpy>=1.19.5
Requires-Dist: ase>=3.24.0
Requires-Dist: networkx>=3.4.2
Provides-Extra: dev
Requires-Dist: pytest>=7.4.0; extra == "dev"
Requires-Dist: pytest-cov>=3.0.0; extra == "dev"
Requires-Dist: ruff>=0.0.285; extra == "dev"
Provides-Extra: docs
Requires-Dist: mkdocs-material>=9.4.0; extra == "docs"
Requires-Dist: mkdocstrings[python]>=0.22.0; extra == "docs"
Requires-Dist: mkdocs-gen-files>=0.5.0; extra == "docs"
Requires-Dist: mkdocs-literate-nav>=0.6.0; extra == "docs"
Requires-Dist: pillow>=10.0.0; extra == "docs"
Requires-Dist: cairosvg>=2.7.1; extra == "docs"
Dynamic: license-file
